dedup_pg/__init__.py
dedup_pg/helpers.py
dedup_pg/index.py
dedup_pg/backend/__init__.py
dedup_pg/backend/backend.py
dedup_pg/backend/sqlalchemy.py
dedup_pg-0.4.2.dist-info/METADATA
dedup_pg-0.4.2.dist-info/WHEEL
dedup_pg-0.4.2.dist-info/top_level.txt
dedup_pg-0.4.2.dist-info/RECORD
