Metadata-Version: 2.4
Name: dedup-pg
Version: 0.4.2
Summary: Postgres indexing utilities to implement high-throughput queries with on-the-fly deduplication
Requires-Python: >=3.11
Requires-Dist: numpy>=2.3.4
Requires-Dist: pytest>=8.4.2
Requires-Dist: xxhash>=3.6.0
Provides-Extra: sqlalchemy
Requires-Dist: psycopg2-binary>=2.9.11; extra == "sqlalchemy"
Requires-Dist: sqlalchemy>=2.0.44; extra == "sqlalchemy"
